<?xml version='1.0' encoding='UTF-8'?>
<!DOCTYPE IdentityRequest PUBLIC "sailpoint.dtd" "sailpoint.dtd">
<IdentityRequest completionStatus="Pending" endDate="1768221026524" executionStatus="Completed" name="0000000299" priority="Normal" requesterDisplayName="The Administrator" requesterId="c0a83c0199cf13658199cf93c73500fe" source="LCM" state="End" targetClass="Identity" targetDisplayName="sumit verma" type="AccessRequest" verified="1768470389186">
  <Attributes>
    <Map>
      <entry key="approvalSummaries">
        <value>
          <List>
            <ApprovalSummary completer="The Administrator" endDate="1768221023676" owner="spadmin" request="Owner Approval - Account Changes for User: sumit verma" startDate="1768220966400" state="Finished" workItemId="c0a83c019b731761819bb22ebdac24eb" workItemType="Approval">
              <ApprovalSet>
                <ApprovalItem application="Financial Planning &amp; Forecasting" approver="spadmin" displayValue="Accounts Receivable Officer" name="roles" nativeIdentity="8512519" operation="Add" state="Finished" value="Accounts Receivable Officer">
                  <Attributes>
                    <Map>
                      <entry key="attachmentConfigList"/>
                      <entry key="attachments"/>
                      <entry key="flow" value="AccessRequest"/>
                      <entry key="id" value="c0a83c019a0512c7819a085c06492769"/>
                      <entry key="interface" value="LCM"/>
                      <entry key="operation" value="EntitlementAdd"/>
                    </Map>
                  </Attributes>
                </ApprovalItem>
                <ApprovalItem application="Financial Planning &amp; Forecasting" approver="spadmin" displayValue="General Ledger Accountant" name="roles" nativeIdentity="8512519" operation="Add" state="Finished" value="General Ledger Accountant">
                  <Attributes>
                    <Map>
                      <entry key="attachmentConfigList"/>
                      <entry key="attachments"/>
                      <entry key="flow" value="AccessRequest"/>
                      <entry key="id" value="c0a83c019a0512c7819a085c066d276d"/>
                      <entry key="interface" value="LCM"/>
                      <entry key="operation" value="EntitlementAdd"/>
                    </Map>
                  </Attributes>
                </ApprovalItem>
              </ApprovalSet>
            </ApprovalSummary>
            <ApprovalSummary completer="The Administrator" endDate="1768221016698" owner="spadmin" request="Owner Approval - Account Changes for User: sumit verma" startDate="1768220966562" state="Finished" workItemId="c0a83c019b731761819bb22ebe4f24ed" workItemType="Approval">
              <ApprovalSet>
                <ApprovalItem application="Sales Analytics" approver="spadmin" displayValue="Incentive &amp; Compensation Analyst" name="roles" nativeIdentity="8512519" operation="Add" state="Finished" value="Incentive &amp; Compensation Analyst">
                  <Attributes>
                    <Map>
                      <entry key="attachmentConfigList"/>
                      <entry key="attachments"/>
                      <entry key="flow" value="AccessRequest"/>
                      <entry key="id" value="c0a83c019a0c102b819a1038f4ca0502"/>
                      <entry key="interface" value="LCM"/>
                      <entry key="nativeIdUpdated">
                        <value>
                          <Boolean>true</Boolean>
                        </value>
                      </entry>
                      <entry key="operation" value="EntitlementAdd"/>
                    </Map>
                  </Attributes>
                </ApprovalItem>
              </ApprovalSet>
            </ApprovalSummary>
          </List>
        </value>
      </entry>
      <entry key="messages">
        <value>
          <List>
            <Message key="notification_failed_no_email" type="Warn">
              <Parameters>
                <String>0c204bd8-d1ae-4615-8678-83a9090ffb53</String>
              </Parameters>
            </Message>
            <Message key="java.sql.SQLIntegrityConstraintViolationException: Duplicate entry '8512519' for key 'salesemployee.PRIMARY'" type="Error"/>
            <Message key="task_msg_identity_request_verification_failed_noIdentity" type="Error">
              <Parameters>
                <String>sumit verma</String>
              </Parameters>
            </Message>
          </List>
        </value>
      </entry>
      <entry key="provisionedProject">
        <value>
          <ProvisioningProject identity="83824b7f-2498-498f-acef-16fc78db0097">
            <Attributes>
              <Map>
                <entry key="disableRetryRequest">
                  <value>
                    <Boolean>true</Boolean>
                  </value>
                </entry>
                <entry key="identityRequestId" value="0000000299"/>
                <entry key="optimisticProvisioning" value="false"/>
                <entry key="requester" value="spadmin"/>
                <entry key="source" value="LCM"/>
              </Map>
            </Attributes>
            <MasterPlan>
              <ProvisioningPlan>
                <AccountRequest application="Financial Planning &amp; Forecasting" nativeIdentity="8512519" op="Modify">
                  <Attributes>
                    <Map>
                      <entry key="attachmentConfigList"/>
                      <entry key="attachments"/>
                      <entry key="flow" value="AccessRequest"/>
                      <entry key="id" value="c0a83c019a0512c7819a085c06492769"/>
                      <entry key="interface" value="LCM"/>
                      <entry key="operation" value="EntitlementAdd"/>
                    </Map>
                  </Attributes>
                  <AttributeRequest displayValue="Accounts Receivable Officer" name="roles" op="Add" value="Accounts Receivable Officer">
                    <Attributes>
                      <Map>
                        <entry key="assignment" value="true"/>
                      </Map>
                    </Attributes>
                  </AttributeRequest>
                </AccountRequest>
                <AccountRequest application="Financial Planning &amp; Forecasting" nativeIdentity="8512519" op="Modify">
                  <Attributes>
                    <Map>
                      <entry key="attachmentConfigList"/>
                      <entry key="attachments"/>
                      <entry key="flow" value="AccessRequest"/>
                      <entry key="id" value="c0a83c019a0512c7819a085c066d276d"/>
                      <entry key="interface" value="LCM"/>
                      <entry key="operation" value="EntitlementAdd"/>
                    </Map>
                  </Attributes>
                  <AttributeRequest displayValue="General Ledger Accountant" name="roles" op="Add" value="General Ledger Accountant">
                    <Attributes>
                      <Map>
                        <entry key="assignment" value="true"/>
                      </Map>
                    </Attributes>
                  </AttributeRequest>
                </AccountRequest>
                <AccountRequest application="Sales Analytics" op="Modify">
                  <Attributes>
                    <Map>
                      <entry key="attachmentConfigList"/>
                      <entry key="attachments"/>
                      <entry key="flow" value="AccessRequest"/>
                      <entry key="id" value="c0a83c019a0c102b819a1038f4ca0502"/>
                      <entry key="interface" value="LCM"/>
                      <entry key="nativeIdUpdated">
                        <value>
                          <Boolean>true</Boolean>
                        </value>
                      </entry>
                      <entry key="operation" value="EntitlementAdd"/>
                    </Map>
                  </Attributes>
                  <AttributeRequest displayValue="Incentive &amp; Compensation Analyst" name="roles" op="Add" value="Incentive &amp; Compensation Analyst">
                    <Attributes>
                      <Map>
                        <entry key="assignment" value="true"/>
                      </Map>
                    </Attributes>
                  </AttributeRequest>
                </AccountRequest>
                <Attributes>
                  <Map>
                    <entry key="identityRequestId" value="0000000299"/>
                    <entry key="requester" value="spadmin"/>
                    <entry key="source" value="LCM"/>
                  </Map>
                </Attributes>
                <ProvisioningTargets>
                  <ProvisioningTarget application="Financial Planning &amp; Forecasting" attribute="roles" value="Accounts Receivable Officer">
                    <AccountSelection applicationId="c0a83c0199d9117b8199d942b544000a" applicationName="Financial Planning &amp; Forecasting" selection="8512519">
                      <AccountInfo displayName="8512519" nativeIdentity="8512519"/>
                    </AccountSelection>
                  </ProvisioningTarget>
                  <ProvisioningTarget application="Financial Planning &amp; Forecasting" attribute="roles" value="General Ledger Accountant">
                    <AccountSelection applicationId="c0a83c0199d9117b8199d942b544000a" applicationName="Financial Planning &amp; Forecasting" selection="8512519">
                      <AccountInfo displayName="8512519" nativeIdentity="8512519"/>
                    </AccountSelection>
                  </ProvisioningTarget>
                  <ProvisioningTarget application="Sales Analytics" attribute="roles" value="Incentive &amp; Compensation Analyst">
                    <AccountSelection applicationId="c0a83c019a0c102b819a102f903504da" applicationName="Sales Analytics" implicitCreate="true"/>
                  </ProvisioningTarget>
                  <ProvisioningTarget retain="true" role="NS_Role_Corporate_Learning_Portal"/>
                  <ProvisioningTarget retain="true" role="SR_Role_Active_Directory_Basic_Access">
                    <AccountSelection applicationId="c0a83c0199d417218199d43c5f300017" applicationName="Active Directory" selection="CN=verma.sumit,OU=Product Management Office (PMO),OU=Permanent Employees,OU=Users,OU=SailPoint,DC=nsiiq,DC=com">
                      <AccountInfo displayName="verma.sumit" nativeIdentity="CN=verma.sumit,OU=Product Management Office (PMO),OU=Permanent Employees,OU=Users,OU=SailPoint,DC=nsiiq,DC=com"/>
                    </AccountSelection>
                  </ProvisioningTarget>
                </ProvisioningTargets>
              </ProvisioningPlan>
            </MasterPlan>
            <ProvisioningPlan nativeIdentity="83824b7f-2498-498f-acef-16fc78db0097" targetIntegration="Financial Planning &amp; Forecasting" trackingId="0b6c944f989b410289c6e26db859d319">
              <AccountRequest application="Financial Planning &amp; Forecasting" nativeIdentity="8512519" op="Modify" targetIntegration="Financial Planning &amp; Forecasting">
                <Attributes>
                  <Map>
                    <entry key="attachmentConfigList"/>
                    <entry key="attachments"/>
                    <entry key="flow" value="AccessRequest"/>
                    <entry key="id" value="c0a83c019a0512c7819a085c066d276d"/>
                    <entry key="interface" value="LCM"/>
                    <entry key="operation" value="EntitlementAdd"/>
                  </Map>
                </Attributes>
                <AttributeRequest displayValue="Accounts Receivable Officer" name="roles" op="Add" value="Accounts Receivable Officer">
                  <Attributes>
                    <Map>
                      <entry key="assignment" value="true"/>
                    </Map>
                  </Attributes>
                </AttributeRequest>
                <AttributeRequest displayValue="General Ledger Accountant" name="roles" op="Add" value="General Ledger Accountant">
                  <Attributes>
                    <Map>
                      <entry key="assignment" value="true"/>
                    </Map>
                  </Attributes>
                </AttributeRequest>
                <ProvisioningResult status="committed"/>
              </AccountRequest>
              <Attributes>
                <Map>
                  <entry key="identityRequestId" value="0000000299"/>
                  <entry key="requester" value="spadmin"/>
                  <entry key="source" value="LCM"/>
                </Map>
              </Attributes>
              <ProvisioningResult status="committed"/>
            </ProvisioningPlan>
            <ProvisioningPlan nativeIdentity="83824b7f-2498-498f-acef-16fc78db0097" targetIntegration="Sales Analytics" trackingId="dd414618a708449f97fdaa937bd54d7a">
              <AccountRequest application="Sales Analytics" nativeIdentity="8512519" op="Create">
                <Attributes>
                  <Map>
                    <entry key="attachmentConfigList"/>
                    <entry key="attachments"/>
                    <entry key="flow" value="AccessRequest"/>
                    <entry key="id" value="c0a83c019a0c102b819a1038f4ca0502"/>
                    <entry key="interface" value="LCM"/>
                    <entry key="nativeIdUpdated">
                      <value>
                        <Boolean>true</Boolean>
                      </value>
                    </entry>
                    <entry key="operation" value="EntitlementAdd"/>
                    <entry key="provisioningTransactionId" value="c0a83c019b731761819bb22fa55a2511"/>
                  </Map>
                </Attributes>
                <AttributeRequest displayValue="Incentive &amp; Compensation Analyst" name="roles" op="Add" value="Incentive &amp; Compensation Analyst">
                  <Attributes>
                    <Map>
                      <entry key="assignment" value="true"/>
                    </Map>
                  </Attributes>
                </AttributeRequest>
                <AttributeRequest name="firstName" op="Set" value="sumit"/>
                <AttributeRequest name="lastName" op="Set" value="verma"/>
                <AttributeRequest name="status" op="Set" value="Active"/>
                <AttributeRequest name="department" op="Set" value="Financial Risk Management"/>
                <AttributeRequest name="userLevel" op="Set" value="A"/>
                <AttributeRequest name="hireDate" op="Set" value="02-01-2026"/>
                <AttributeRequest name="salesQuota" op="Set" value="500000"/>
                <AttributeRequest name="achievedSales" op="Set" value="0"/>
                <AttributeRequest name="terminationDate" op="Set" value="12-26-2027"/>
                <AttributeRequest name="workState" op="Set" value="CN - Guangzhou"/>
                <AttributeRequest name="email" op="Set" value="verma.sumit@nstechiiq.com"/>
                <AttributeRequest name="region" op="Set" value="A"/>
                <AttributeRequest name="territory" op="Set" value="A"/>
                <AttributeRequest name="commissionRate" op="Set" value="5%"/>
                <AttributeRequest name="managerId" op="Set" value="c06fe45e-ee86-4c73-8bdb-73ca28e2cd69"/>
                <AttributeRequest name="annualHours" op="Set" value="720"/>
                <AttributeRequest name="jobTitle" op="Set" value="Product Manager-test"/>
                <AttributeRequest name="country" op="Set" value="China"/>
                <AttributeRequest name="isManager" op="Set" value="No"/>
                <AttributeRequest name="businessUnit" op="Set" value="A"/>
                <ProvisioningResult status="failed">
                  <Errors>
                    <Message key="java.sql.SQLIntegrityConstraintViolationException: Duplicate entry '8512519' for key 'salesemployee.PRIMARY'" type="Error"/>
                  </Errors>
                </ProvisioningResult>
              </AccountRequest>
              <Attributes>
                <Map>
                  <entry key="identityRequestId" value="0000000299"/>
                  <entry key="requester" value="spadmin"/>
                  <entry key="source" value="LCM"/>
                </Map>
              </Attributes>
              <ProvisioningResult status="failed">
                <Errors>
                  <Message key="java.sql.SQLIntegrityConstraintViolationException: Duplicate entry '8512519' for key 'salesemployee.PRIMARY'" type="Error"/>
                </Errors>
              </ProvisioningResult>
            </ProvisioningPlan>
            <ProvisioningTarget application="Financial Planning &amp; Forecasting" attribute="roles" value="Accounts Receivable Officer">
              <AccountSelection applicationId="c0a83c0199d9117b8199d942b544000a" applicationName="Financial Planning &amp; Forecasting" selection="8512519">
                <AccountInfo displayName="8512519" nativeIdentity="8512519"/>
              </AccountSelection>
            </ProvisioningTarget>
            <ProvisioningTarget application="Financial Planning &amp; Forecasting" attribute="roles" value="General Ledger Accountant">
              <AccountSelection applicationId="c0a83c0199d9117b8199d942b544000a" applicationName="Financial Planning &amp; Forecasting" selection="8512519">
                <AccountInfo displayName="8512519" nativeIdentity="8512519"/>
              </AccountSelection>
            </ProvisioningTarget>
            <ProvisioningTarget application="Sales Analytics" attribute="roles" value="Incentive &amp; Compensation Analyst">
              <AccountSelection applicationId="c0a83c019a0c102b819a102f903504da" applicationName="Sales Analytics" implicitCreate="true"/>
            </ProvisioningTarget>
            <ProvisioningTarget retain="true" role="NS_Role_Corporate_Learning_Portal"/>
            <ProvisioningTarget retain="true" role="SR_Role_Active_Directory_Basic_Access">
              <AccountSelection applicationId="c0a83c0199d417218199d43c5f300017" applicationName="Active Directory" selection="CN=verma.sumit,OU=Product Management Office (PMO),OU=Permanent Employees,OU=Users,OU=SailPoint,DC=nsiiq,DC=com">
                <AccountInfo displayName="verma.sumit" nativeIdentity="CN=verma.sumit,OU=Product Management Office (PMO),OU=Permanent Employees,OU=Users,OU=SailPoint,DC=nsiiq,DC=com"/>
              </AccountSelection>
            </ProvisioningTarget>
          </ProvisioningProject>
        </value>
      </entry>
      <entry key="taskResultId" value="c0a83c019b731761819bb22ebaf524e5"/>
    </Map>
  </Attributes>
  <RequestItems>
    <IdentityRequestItem application="Financial Planning &amp; Forecasting" approvalState="Finished" approverName="spadmin" name="roles" nativeIdentity="8512519" operation="Add" ownerName="spadmin" provisioningEngine="Financial Planning &amp; Forecasting" provisioningState="Finished" value="Accounts Receivable Officer">
      <Attributes>
        <Map>
          <entry key="assignmentId" value="bbfe28bac893426689187860ac2d7b6f"/>
          <entry key="attachmentConfigList"/>
          <entry key="attachments"/>
          <entry key="flow" value="AccessRequest"/>
          <entry key="id" value="c0a83c019a0512c7819a085c06492769"/>
          <entry key="identityEntitlementId" value="c0a83c019b731761819bb22fa138250e"/>
          <entry key="interface" value="LCM"/>
          <entry key="managedAttributeType" value="Entitlement"/>
          <entry key="operation" value="EntitlementAdd"/>
          <entry key="provisioningPlan">
            <value>
              <ProvisioningPlan trackingId="168d671fcc0e4df39a779ac7deef85d8">
                <AccountRequest application="Financial Planning &amp; Forecasting" nativeIdentity="8512519" op="Modify" targetIntegration="Financial Planning &amp; Forecasting">
                  <Attributes>
                    <Map>
                      <entry key="attachmentConfigList"/>
                      <entry key="attachments"/>
                      <entry key="flow" value="AccessRequest"/>
                      <entry key="id" value="c0a83c019a0512c7819a085c066d276d"/>
                      <entry key="interface" value="LCM"/>
                      <entry key="operation" value="EntitlementAdd"/>
                    </Map>
                  </Attributes>
                  <AttributeRequest displayValue="Accounts Receivable Officer" name="roles" op="Add" trackingId="168d671fcc0e4df39a779ac7deef85d8" value="Accounts Receivable Officer">
                    <Attributes>
                      <Map>
                        <entry key="assignment" value="true"/>
                      </Map>
                    </Attributes>
                  </AttributeRequest>
                </AccountRequest>
                <Attributes>
                  <Map>
                    <entry key="source" value="LCM"/>
                  </Map>
                </Attributes>
              </ProvisioningPlan>
            </value>
          </entry>
        </Map>
      </Attributes>
      <Owner>
        <Reference class="sailpoint.object.Identity" name="spadmin"/>
      </Owner>
    </IdentityRequestItem>
    <IdentityRequestItem application="Financial Planning &amp; Forecasting" approvalState="Finished" approverName="spadmin" name="roles" nativeIdentity="8512519" operation="Add" ownerName="spadmin" provisioningEngine="Financial Planning &amp; Forecasting" provisioningState="Commited" value="General Ledger Accountant">
      <Attributes>
        <Map>
          <entry key="assignmentId" value="eb8229473a2f41ffaba8fccea9bab81b"/>
          <entry key="attachmentConfigList"/>
          <entry key="attachments"/>
          <entry key="flow" value="AccessRequest"/>
          <entry key="id" value="c0a83c019a0512c7819a085c066d276d"/>
          <entry key="identityEntitlementId" value="c0a83c019b731761819bb22fa140250f"/>
          <entry key="interface" value="LCM"/>
          <entry key="managedAttributeType" value="Entitlement"/>
          <entry key="operation" value="EntitlementAdd"/>
          <entry key="provisioningPlan">
            <value>
              <ProvisioningPlan trackingId="a35641a9400047c589e2acac863829f3">
                <AccountRequest application="Financial Planning &amp; Forecasting" nativeIdentity="8512519" op="Modify" targetIntegration="Financial Planning &amp; Forecasting">
                  <Attributes>
                    <Map>
                      <entry key="attachmentConfigList"/>
                      <entry key="attachments"/>
                      <entry key="flow" value="AccessRequest"/>
                      <entry key="id" value="c0a83c019a0512c7819a085c066d276d"/>
                      <entry key="interface" value="LCM"/>
                      <entry key="operation" value="EntitlementAdd"/>
                    </Map>
                  </Attributes>
                  <AttributeRequest displayValue="General Ledger Accountant" name="roles" op="Add" trackingId="a35641a9400047c589e2acac863829f3" value="General Ledger Accountant">
                    <Attributes>
                      <Map>
                        <entry key="assignment" value="true"/>
                      </Map>
                    </Attributes>
                  </AttributeRequest>
                </AccountRequest>
                <Attributes>
                  <Map>
                    <entry key="source" value="LCM"/>
                  </Map>
                </Attributes>
              </ProvisioningPlan>
            </value>
          </entry>
        </Map>
      </Attributes>
      <Owner>
        <Reference class="sailpoint.object.Identity" name="spadmin"/>
      </Owner>
    </IdentityRequestItem>
    <IdentityRequestItem application="Sales Analytics" approvalState="Finished" approverName="spadmin" name="roles" nativeIdentity="8512519" operation="Add" ownerName="spadmin" provisioningEngine="Sales Analytics" provisioningState="Failed" value="Incentive &amp; Compensation Analyst">
      <Attributes>
        <Map>
          <entry key="assignmentId" value="7a422a15f0e64ed1bce2abca568f7b1b"/>
          <entry key="attachmentConfigList"/>
          <entry key="attachments"/>
          <entry key="errors">
            <value>
              <List>
                <Message key="java.sql.SQLIntegrityConstraintViolationException: Duplicate entry '8512519' for key 'salesemployee.PRIMARY'" type="Error"/>
              </List>
            </value>
          </entry>
          <entry key="flow" value="AccessRequest"/>
          <entry key="id" value="c0a83c019a0c102b819a1038f4ca0502"/>
          <entry key="identityEntitlementId" value="c0a83c019b731761819bb22fa1472510"/>
          <entry key="interface" value="LCM"/>
          <entry key="managedAttributeType" value="Entitlement"/>
          <entry key="operation" value="EntitlementAdd"/>
          <entry key="provisioningPlan">
            <value>
              <ProvisioningPlan trackingId="20121dbc47914636acfea0a02c340417">
                <AccountRequest application="Sales Analytics" nativeIdentity="8512519" op="Create">
                  <Attributes>
                    <Map>
                      <entry key="attachmentConfigList"/>
                      <entry key="attachments"/>
                      <entry key="flow" value="AccessRequest"/>
                      <entry key="id" value="c0a83c019a0c102b819a1038f4ca0502"/>
                      <entry key="interface" value="LCM"/>
                      <entry key="nativeIdUpdated">
                        <value>
                          <Boolean>true</Boolean>
                        </value>
                      </entry>
                      <entry key="operation" value="EntitlementAdd"/>
                      <entry key="provisioningTransactionId" value="c0a83c019b731761819bb22fa55a2511"/>
                    </Map>
                  </Attributes>
                  <AttributeRequest displayValue="Incentive &amp; Compensation Analyst" name="roles" op="Add" trackingId="20121dbc47914636acfea0a02c340417" value="Incentive &amp; Compensation Analyst">
                    <Attributes>
                      <Map>
                        <entry key="assignment" value="true"/>
                      </Map>
                    </Attributes>
                  </AttributeRequest>
                </AccountRequest>
                <Attributes>
                  <Map>
                    <entry key="source" value="LCM"/>
                  </Map>
                </Attributes>
              </ProvisioningPlan>
            </value>
          </entry>
        </Map>
      </Attributes>
      <Owner>
        <Reference class="sailpoint.object.Identity" name="spadmin"/>
      </Owner>
    </IdentityRequestItem>
    <IdentityRequestItem application="Sales Analytics" approvalState="Finished" compilationStatus="Expansion" expansionCause="ProvisioningPolicy" name="firstName" nativeIdentity="8512519" operation="Set" provisioningEngine="Sales Analytics" provisioningState="Failed" value="sumit">
      <Attributes>
        <Map>
          <entry key="attachmentConfigList"/>
          <entry key="attachments"/>
          <entry key="errors">
            <value>
              <List>
                <Message key="java.sql.SQLIntegrityConstraintViolationException: Duplicate entry '8512519' for key 'salesemployee.PRIMARY'" type="Error"/>
              </List>
            </value>
          </entry>
          <entry key="expansionInfo" value="Sales Analytics"/>
          <entry key="flow" value="AccessRequest"/>
          <entry key="id" value="c0a83c019a0c102b819a1038f4ca0502"/>
          <entry key="interface" value="LCM"/>
          <entry key="managedAttributeType" value="Entitlement"/>
          <entry key="nativeIdUpdated">
            <value>
              <Boolean>true</Boolean>
            </value>
          </entry>
          <entry key="operation" value="EntitlementAdd"/>
          <entry key="provisioningPlan">
            <value>
              <ProvisioningPlan trackingId="c36ce592092940d6b20de9cb303bbace">
                <AccountRequest application="Sales Analytics" nativeIdentity="8512519" op="Create">
                  <Attributes>
                    <Map>
                      <entry key="attachmentConfigList"/>
                      <entry key="attachments"/>
                      <entry key="flow" value="AccessRequest"/>
                      <entry key="id" value="c0a83c019a0c102b819a1038f4ca0502"/>
                      <entry key="interface" value="LCM"/>
                      <entry key="nativeIdUpdated">
                        <value>
                          <Boolean>true</Boolean>
                        </value>
                      </entry>
                      <entry key="operation" value="EntitlementAdd"/>
                      <entry key="provisioningTransactionId" value="c0a83c019b731761819bb22fa55a2511"/>
                    </Map>
                  </Attributes>
                  <AttributeRequest name="firstName" op="Set" trackingId="c36ce592092940d6b20de9cb303bbace" value="sumit"/>
                </AccountRequest>
                <Attributes>
                  <Map>
                    <entry key="source" value="LCM"/>
                  </Map>
                </Attributes>
              </ProvisioningPlan>
            </value>
          </entry>
        </Map>
      </Attributes>
    </IdentityRequestItem>
    <IdentityRequestItem application="Sales Analytics" approvalState="Finished" compilationStatus="Expansion" expansionCause="ProvisioningPolicy" name="lastName" nativeIdentity="8512519" operation="Set" provisioningEngine="Sales Analytics" provisioningState="Failed" value="verma">
      <Attributes>
        <Map>
          <entry key="attachmentConfigList"/>
          <entry key="attachments"/>
          <entry key="errors">
            <value>
              <List>
                <Message key="java.sql.SQLIntegrityConstraintViolationException: Duplicate entry '8512519' for key 'salesemployee.PRIMARY'" type="Error"/>
              </List>
            </value>
          </entry>
          <entry key="expansionInfo" value="Sales Analytics"/>
          <entry key="flow" value="AccessRequest"/>
          <entry key="id" value="c0a83c019a0c102b819a1038f4ca0502"/>
          <entry key="interface" value="LCM"/>
          <entry key="managedAttributeType" value="Entitlement"/>
          <entry key="nativeIdUpdated">
            <value>
              <Boolean>true</Boolean>
            </value>
          </entry>
          <entry key="operation" value="EntitlementAdd"/>
          <entry key="provisioningPlan">
            <value>
              <ProvisioningPlan trackingId="fc878a6d2e93402b87286223698fa2b9">
                <AccountRequest application="Sales Analytics" nativeIdentity="8512519" op="Create">
                  <Attributes>
                    <Map>
                      <entry key="attachmentConfigList"/>
                      <entry key="attachments"/>
                      <entry key="flow" value="AccessRequest"/>
                      <entry key="id" value="c0a83c019a0c102b819a1038f4ca0502"/>
                      <entry key="interface" value="LCM"/>
                      <entry key="nativeIdUpdated">
                        <value>
                          <Boolean>true</Boolean>
                        </value>
                      </entry>
                      <entry key="operation" value="EntitlementAdd"/>
                      <entry key="provisioningTransactionId" value="c0a83c019b731761819bb22fa55a2511"/>
                    </Map>
                  </Attributes>
                  <AttributeRequest name="lastName" op="Set" trackingId="fc878a6d2e93402b87286223698fa2b9" value="verma"/>
                </AccountRequest>
                <Attributes>
                  <Map>
                    <entry key="source" value="LCM"/>
                  </Map>
                </Attributes>
              </ProvisioningPlan>
            </value>
          </entry>
        </Map>
      </Attributes>
    </IdentityRequestItem>
    <IdentityRequestItem application="Sales Analytics" approvalState="Finished" compilationStatus="Expansion" expansionCause="ProvisioningPolicy" name="status" nativeIdentity="8512519" operation="Set" provisioningEngine="Sales Analytics" provisioningState="Failed" value="Active">
      <Attributes>
        <Map>
          <entry key="attachmentConfigList"/>
          <entry key="attachments"/>
          <entry key="errors">
            <value>
              <List>
                <Message key="java.sql.SQLIntegrityConstraintViolationException: Duplicate entry '8512519' for key 'salesemployee.PRIMARY'" type="Error"/>
              </List>
            </value>
          </entry>
          <entry key="expansionInfo" value="Sales Analytics"/>
          <entry key="flow" value="AccessRequest"/>
          <entry key="id" value="c0a83c019a0c102b819a1038f4ca0502"/>
          <entry key="interface" value="LCM"/>
          <entry key="managedAttributeType" value="Entitlement"/>
          <entry key="nativeIdUpdated">
            <value>
              <Boolean>true</Boolean>
            </value>
          </entry>
          <entry key="operation" value="EntitlementAdd"/>
          <entry key="provisioningPlan">
            <value>
              <ProvisioningPlan trackingId="029380f08866412a8806c54857327859">
                <AccountRequest application="Sales Analytics" nativeIdentity="8512519" op="Create">
                  <Attributes>
                    <Map>
                      <entry key="attachmentConfigList"/>
                      <entry key="attachments"/>
                      <entry key="flow" value="AccessRequest"/>
                      <entry key="id" value="c0a83c019a0c102b819a1038f4ca0502"/>
                      <entry key="interface" value="LCM"/>
                      <entry key="nativeIdUpdated">
                        <value>
                          <Boolean>true</Boolean>
                        </value>
                      </entry>
                      <entry key="operation" value="EntitlementAdd"/>
                      <entry key="provisioningTransactionId" value="c0a83c019b731761819bb22fa55a2511"/>
                    </Map>
                  </Attributes>
                  <AttributeRequest name="status" op="Set" trackingId="029380f08866412a8806c54857327859" value="Active"/>
                </AccountRequest>
                <Attributes>
                  <Map>
                    <entry key="source" value="LCM"/>
                  </Map>
                </Attributes>
              </ProvisioningPlan>
            </value>
          </entry>
        </Map>
      </Attributes>
    </IdentityRequestItem>
    <IdentityRequestItem application="Sales Analytics" approvalState="Finished" compilationStatus="Expansion" expansionCause="ProvisioningPolicy" name="department" nativeIdentity="8512519" operation="Set" provisioningEngine="Sales Analytics" provisioningState="Failed" value="Financial Risk Management">
      <Attributes>
        <Map>
          <entry key="attachmentConfigList"/>
          <entry key="attachments"/>
          <entry key="errors">
            <value>
              <List>
                <Message key="java.sql.SQLIntegrityConstraintViolationException: Duplicate entry '8512519' for key 'salesemployee.PRIMARY'" type="Error"/>
              </List>
            </value>
          </entry>
          <entry key="expansionInfo" value="Sales Analytics"/>
          <entry key="flow" value="AccessRequest"/>
          <entry key="id" value="c0a83c019a0c102b819a1038f4ca0502"/>
          <entry key="interface" value="LCM"/>
          <entry key="managedAttributeType" value="Entitlement"/>
          <entry key="nativeIdUpdated">
            <value>
              <Boolean>true</Boolean>
            </value>
          </entry>
          <entry key="operation" value="EntitlementAdd"/>
          <entry key="provisioningPlan">
            <value>
              <ProvisioningPlan trackingId="b081568a8cb84087a7d1f055d4c5cd08">
                <AccountRequest application="Sales Analytics" nativeIdentity="8512519" op="Create">
                  <Attributes>
                    <Map>
                      <entry key="attachmentConfigList"/>
                      <entry key="attachments"/>
                      <entry key="flow" value="AccessRequest"/>
                      <entry key="id" value="c0a83c019a0c102b819a1038f4ca0502"/>
                      <entry key="interface" value="LCM"/>
                      <entry key="nativeIdUpdated">
                        <value>
                          <Boolean>true</Boolean>
                        </value>
                      </entry>
                      <entry key="operation" value="EntitlementAdd"/>
                      <entry key="provisioningTransactionId" value="c0a83c019b731761819bb22fa55a2511"/>
                    </Map>
                  </Attributes>
                  <AttributeRequest name="department" op="Set" trackingId="b081568a8cb84087a7d1f055d4c5cd08" value="Financial Risk Management"/>
                </AccountRequest>
                <Attributes>
                  <Map>
                    <entry key="source" value="LCM"/>
                  </Map>
                </Attributes>
              </ProvisioningPlan>
            </value>
          </entry>
        </Map>
      </Attributes>
    </IdentityRequestItem>
    <IdentityRequestItem application="Sales Analytics" approvalState="Finished" compilationStatus="Expansion" expansionCause="ProvisioningPolicy" name="userLevel" nativeIdentity="8512519" operation="Set" provisioningEngine="Sales Analytics" provisioningState="Failed" value="A">
      <Attributes>
        <Map>
          <entry key="attachmentConfigList"/>
          <entry key="attachments"/>
          <entry key="errors">
            <value>
              <List>
                <Message key="java.sql.SQLIntegrityConstraintViolationException: Duplicate entry '8512519' for key 'salesemployee.PRIMARY'" type="Error"/>
              </List>
            </value>
          </entry>
          <entry key="expansionInfo" value="Sales Analytics"/>
          <entry key="flow" value="AccessRequest"/>
          <entry key="id" value="c0a83c019a0c102b819a1038f4ca0502"/>
          <entry key="interface" value="LCM"/>
          <entry key="managedAttributeType" value="Entitlement"/>
          <entry key="nativeIdUpdated">
            <value>
              <Boolean>true</Boolean>
            </value>
          </entry>
          <entry key="operation" value="EntitlementAdd"/>
          <entry key="provisioningPlan">
            <value>
              <ProvisioningPlan trackingId="406905f889e24f82afd2b8dfa75ef0fe">
                <AccountRequest application="Sales Analytics" nativeIdentity="8512519" op="Create">
                  <Attributes>
                    <Map>
                      <entry key="attachmentConfigList"/>
                      <entry key="attachments"/>
                      <entry key="flow" value="AccessRequest"/>
                      <entry key="id" value="c0a83c019a0c102b819a1038f4ca0502"/>
                      <entry key="interface" value="LCM"/>
                      <entry key="nativeIdUpdated">
                        <value>
                          <Boolean>true</Boolean>
                        </value>
                      </entry>
                      <entry key="operation" value="EntitlementAdd"/>
                      <entry key="provisioningTransactionId" value="c0a83c019b731761819bb22fa55a2511"/>
                    </Map>
                  </Attributes>
                  <AttributeRequest name="userLevel" op="Set" trackingId="406905f889e24f82afd2b8dfa75ef0fe" value="A"/>
                </AccountRequest>
                <Attributes>
                  <Map>
                    <entry key="source" value="LCM"/>
                  </Map>
                </Attributes>
              </ProvisioningPlan>
            </value>
          </entry>
        </Map>
      </Attributes>
    </IdentityRequestItem>
    <IdentityRequestItem application="Sales Analytics" approvalState="Finished" compilationStatus="Expansion" expansionCause="ProvisioningPolicy" name="hireDate" nativeIdentity="8512519" operation="Set" provisioningEngine="Sales Analytics" provisioningState="Failed" value="02-01-2026">
      <Attributes>
        <Map>
          <entry key="attachmentConfigList"/>
          <entry key="attachments"/>
          <entry key="errors">
            <value>
              <List>
                <Message key="java.sql.SQLIntegrityConstraintViolationException: Duplicate entry '8512519' for key 'salesemployee.PRIMARY'" type="Error"/>
              </List>
            </value>
          </entry>
          <entry key="expansionInfo" value="Sales Analytics"/>
          <entry key="flow" value="AccessRequest"/>
          <entry key="id" value="c0a83c019a0c102b819a1038f4ca0502"/>
          <entry key="interface" value="LCM"/>
          <entry key="managedAttributeType" value="Entitlement"/>
          <entry key="nativeIdUpdated">
            <value>
              <Boolean>true</Boolean>
            </value>
          </entry>
          <entry key="operation" value="EntitlementAdd"/>
          <entry key="provisioningPlan">
            <value>
              <ProvisioningPlan trackingId="654616706b254921b934fa6cb0f264f6">
                <AccountRequest application="Sales Analytics" nativeIdentity="8512519" op="Create">
                  <Attributes>
                    <Map>
                      <entry key="attachmentConfigList"/>
                      <entry key="attachments"/>
                      <entry key="flow" value="AccessRequest"/>
                      <entry key="id" value="c0a83c019a0c102b819a1038f4ca0502"/>
                      <entry key="interface" value="LCM"/>
                      <entry key="nativeIdUpdated">
                        <value>
                          <Boolean>true</Boolean>
                        </value>
                      </entry>
                      <entry key="operation" value="EntitlementAdd"/>
                      <entry key="provisioningTransactionId" value="c0a83c019b731761819bb22fa55a2511"/>
                    </Map>
                  </Attributes>
                  <AttributeRequest name="hireDate" op="Set" trackingId="654616706b254921b934fa6cb0f264f6" value="02-01-2026"/>
                </AccountRequest>
                <Attributes>
                  <Map>
                    <entry key="source" value="LCM"/>
                  </Map>
                </Attributes>
              </ProvisioningPlan>
            </value>
          </entry>
        </Map>
      </Attributes>
    </IdentityRequestItem>
    <IdentityRequestItem application="Sales Analytics" approvalState="Finished" compilationStatus="Expansion" expansionCause="ProvisioningPolicy" name="salesQuota" nativeIdentity="8512519" operation="Set" provisioningEngine="Sales Analytics" provisioningState="Failed" value="500000">
      <Attributes>
        <Map>
          <entry key="attachmentConfigList"/>
          <entry key="attachments"/>
          <entry key="errors">
            <value>
              <List>
                <Message key="java.sql.SQLIntegrityConstraintViolationException: Duplicate entry '8512519' for key 'salesemployee.PRIMARY'" type="Error"/>
              </List>
            </value>
          </entry>
          <entry key="expansionInfo" value="Sales Analytics"/>
          <entry key="flow" value="AccessRequest"/>
          <entry key="id" value="c0a83c019a0c102b819a1038f4ca0502"/>
          <entry key="interface" value="LCM"/>
          <entry key="managedAttributeType" value="Entitlement"/>
          <entry key="nativeIdUpdated">
            <value>
              <Boolean>true</Boolean>
            </value>
          </entry>
          <entry key="operation" value="EntitlementAdd"/>
          <entry key="provisioningPlan">
            <value>
              <ProvisioningPlan trackingId="bc972e1e7530455890979458b3335430">
                <AccountRequest application="Sales Analytics" nativeIdentity="8512519" op="Create">
                  <Attributes>
                    <Map>
                      <entry key="attachmentConfigList"/>
                      <entry key="attachments"/>
                      <entry key="flow" value="AccessRequest"/>
                      <entry key="id" value="c0a83c019a0c102b819a1038f4ca0502"/>
                      <entry key="interface" value="LCM"/>
                      <entry key="nativeIdUpdated">
                        <value>
                          <Boolean>true</Boolean>
                        </value>
                      </entry>
                      <entry key="operation" value="EntitlementAdd"/>
                      <entry key="provisioningTransactionId" value="c0a83c019b731761819bb22fa55a2511"/>
                    </Map>
                  </Attributes>
                  <AttributeRequest name="salesQuota" op="Set" trackingId="bc972e1e7530455890979458b3335430" value="500000"/>
                </AccountRequest>
                <Attributes>
                  <Map>
                    <entry key="source" value="LCM"/>
                  </Map>
                </Attributes>
              </ProvisioningPlan>
            </value>
          </entry>
        </Map>
      </Attributes>
    </IdentityRequestItem>
    <IdentityRequestItem application="Sales Analytics" approvalState="Finished" compilationStatus="Expansion" expansionCause="ProvisioningPolicy" name="achievedSales" nativeIdentity="8512519" operation="Set" provisioningEngine="Sales Analytics" provisioningState="Failed" value="0">
      <Attributes>
        <Map>
          <entry key="attachmentConfigList"/>
          <entry key="attachments"/>
          <entry key="errors">
            <value>
              <List>
                <Message key="java.sql.SQLIntegrityConstraintViolationException: Duplicate entry '8512519' for key 'salesemployee.PRIMARY'" type="Error"/>
              </List>
            </value>
          </entry>
          <entry key="expansionInfo" value="Sales Analytics"/>
          <entry key="flow" value="AccessRequest"/>
          <entry key="id" value="c0a83c019a0c102b819a1038f4ca0502"/>
          <entry key="interface" value="LCM"/>
          <entry key="managedAttributeType" value="Entitlement"/>
          <entry key="nativeIdUpdated">
            <value>
              <Boolean>true</Boolean>
            </value>
          </entry>
          <entry key="operation" value="EntitlementAdd"/>
          <entry key="provisioningPlan">
            <value>
              <ProvisioningPlan trackingId="52707a7df0ce4e3e9461a67d437d03aa">
                <AccountRequest application="Sales Analytics" nativeIdentity="8512519" op="Create">
                  <Attributes>
                    <Map>
                      <entry key="attachmentConfigList"/>
                      <entry key="attachments"/>
                      <entry key="flow" value="AccessRequest"/>
                      <entry key="id" value="c0a83c019a0c102b819a1038f4ca0502"/>
                      <entry key="interface" value="LCM"/>
                      <entry key="nativeIdUpdated">
                        <value>
                          <Boolean>true</Boolean>
                        </value>
                      </entry>
                      <entry key="operation" value="EntitlementAdd"/>
                      <entry key="provisioningTransactionId" value="c0a83c019b731761819bb22fa55a2511"/>
                    </Map>
                  </Attributes>
                  <AttributeRequest name="achievedSales" op="Set" trackingId="52707a7df0ce4e3e9461a67d437d03aa" value="0"/>
                </AccountRequest>
                <Attributes>
                  <Map>
                    <entry key="source" value="LCM"/>
                  </Map>
                </Attributes>
              </ProvisioningPlan>
            </value>
          </entry>
        </Map>
      </Attributes>
    </IdentityRequestItem>
    <IdentityRequestItem application="Sales Analytics" approvalState="Finished" compilationStatus="Expansion" expansionCause="ProvisioningPolicy" name="terminationDate" nativeIdentity="8512519" operation="Set" provisioningEngine="Sales Analytics" provisioningState="Failed" value="12-26-2027">
      <Attributes>
        <Map>
          <entry key="attachmentConfigList"/>
          <entry key="attachments"/>
          <entry key="errors">
            <value>
              <List>
                <Message key="java.sql.SQLIntegrityConstraintViolationException: Duplicate entry '8512519' for key 'salesemployee.PRIMARY'" type="Error"/>
              </List>
            </value>
          </entry>
          <entry key="expansionInfo" value="Sales Analytics"/>
          <entry key="flow" value="AccessRequest"/>
          <entry key="id" value="c0a83c019a0c102b819a1038f4ca0502"/>
          <entry key="interface" value="LCM"/>
          <entry key="managedAttributeType" value="Entitlement"/>
          <entry key="nativeIdUpdated">
            <value>
              <Boolean>true</Boolean>
            </value>
          </entry>
          <entry key="operation" value="EntitlementAdd"/>
          <entry key="provisioningPlan">
            <value>
              <ProvisioningPlan trackingId="8a328187e85c462ebe4e8ba4e84bea72">
                <AccountRequest application="Sales Analytics" nativeIdentity="8512519" op="Create">
                  <Attributes>
                    <Map>
                      <entry key="attachmentConfigList"/>
                      <entry key="attachments"/>
                      <entry key="flow" value="AccessRequest"/>
                      <entry key="id" value="c0a83c019a0c102b819a1038f4ca0502"/>
                      <entry key="interface" value="LCM"/>
                      <entry key="nativeIdUpdated">
                        <value>
                          <Boolean>true</Boolean>
                        </value>
                      </entry>
                      <entry key="operation" value="EntitlementAdd"/>
                      <entry key="provisioningTransactionId" value="c0a83c019b731761819bb22fa55a2511"/>
                    </Map>
                  </Attributes>
                  <AttributeRequest name="terminationDate" op="Set" trackingId="8a328187e85c462ebe4e8ba4e84bea72" value="12-26-2027"/>
                </AccountRequest>
                <Attributes>
                  <Map>
                    <entry key="source" value="LCM"/>
                  </Map>
                </Attributes>
              </ProvisioningPlan>
            </value>
          </entry>
        </Map>
      </Attributes>
    </IdentityRequestItem>
    <IdentityRequestItem application="Sales Analytics" approvalState="Finished" compilationStatus="Expansion" expansionCause="ProvisioningPolicy" name="workState" nativeIdentity="8512519" operation="Set" provisioningEngine="Sales Analytics" provisioningState="Failed" value="CN - Guangzhou">
      <Attributes>
        <Map>
          <entry key="attachmentConfigList"/>
          <entry key="attachments"/>
          <entry key="errors">
            <value>
              <List>
                <Message key="java.sql.SQLIntegrityConstraintViolationException: Duplicate entry '8512519' for key 'salesemployee.PRIMARY'" type="Error"/>
              </List>
            </value>
          </entry>
          <entry key="expansionInfo" value="Sales Analytics"/>
          <entry key="flow" value="AccessRequest"/>
          <entry key="id" value="c0a83c019a0c102b819a1038f4ca0502"/>
          <entry key="interface" value="LCM"/>
          <entry key="managedAttributeType" value="Entitlement"/>
          <entry key="nativeIdUpdated">
            <value>
              <Boolean>true</Boolean>
            </value>
          </entry>
          <entry key="operation" value="EntitlementAdd"/>
          <entry key="provisioningPlan">
            <value>
              <ProvisioningPlan trackingId="c0264a0de9b34e9dacaf59393ccd2716">
                <AccountRequest application="Sales Analytics" nativeIdentity="8512519" op="Create">
                  <Attributes>
                    <Map>
                      <entry key="attachmentConfigList"/>
                      <entry key="attachments"/>
                      <entry key="flow" value="AccessRequest"/>
                      <entry key="id" value="c0a83c019a0c102b819a1038f4ca0502"/>
                      <entry key="interface" value="LCM"/>
                      <entry key="nativeIdUpdated">
                        <value>
                          <Boolean>true</Boolean>
                        </value>
                      </entry>
                      <entry key="operation" value="EntitlementAdd"/>
                      <entry key="provisioningTransactionId" value="c0a83c019b731761819bb22fa55a2511"/>
                    </Map>
                  </Attributes>
                  <AttributeRequest name="workState" op="Set" trackingId="c0264a0de9b34e9dacaf59393ccd2716" value="CN - Guangzhou"/>
                </AccountRequest>
                <Attributes>
                  <Map>
                    <entry key="source" value="LCM"/>
                  </Map>
                </Attributes>
              </ProvisioningPlan>
            </value>
          </entry>
        </Map>
      </Attributes>
    </IdentityRequestItem>
    <IdentityRequestItem application="Sales Analytics" approvalState="Finished" compilationStatus="Expansion" expansionCause="ProvisioningPolicy" name="email" nativeIdentity="8512519" operation="Set" provisioningEngine="Sales Analytics" provisioningState="Failed" value="verma.sumit@nstechiiq.com">
      <Attributes>
        <Map>
          <entry key="attachmentConfigList"/>
          <entry key="attachments"/>
          <entry key="errors">
            <value>
              <List>
                <Message key="java.sql.SQLIntegrityConstraintViolationException: Duplicate entry '8512519' for key 'salesemployee.PRIMARY'" type="Error"/>
              </List>
            </value>
          </entry>
          <entry key="expansionInfo" value="Sales Analytics"/>
          <entry key="flow" value="AccessRequest"/>
          <entry key="id" value="c0a83c019a0c102b819a1038f4ca0502"/>
          <entry key="interface" value="LCM"/>
          <entry key="managedAttributeType" value="Entitlement"/>
          <entry key="nativeIdUpdated">
            <value>
              <Boolean>true</Boolean>
            </value>
          </entry>
          <entry key="operation" value="EntitlementAdd"/>
          <entry key="provisioningPlan">
            <value>
              <ProvisioningPlan trackingId="ead96d1c941c41158a7994f20f20dc70">
                <AccountRequest application="Sales Analytics" nativeIdentity="8512519" op="Create">
                  <Attributes>
                    <Map>
                      <entry key="attachmentConfigList"/>
                      <entry key="attachments"/>
                      <entry key="flow" value="AccessRequest"/>
                      <entry key="id" value="c0a83c019a0c102b819a1038f4ca0502"/>
                      <entry key="interface" value="LCM"/>
                      <entry key="nativeIdUpdated">
                        <value>
                          <Boolean>true</Boolean>
                        </value>
                      </entry>
                      <entry key="operation" value="EntitlementAdd"/>
                      <entry key="provisioningTransactionId" value="c0a83c019b731761819bb22fa55a2511"/>
                    </Map>
                  </Attributes>
                  <AttributeRequest name="email" op="Set" trackingId="ead96d1c941c41158a7994f20f20dc70" value="verma.sumit@nstechiiq.com"/>
                </AccountRequest>
                <Attributes>
                  <Map>
                    <entry key="source" value="LCM"/>
                  </Map>
                </Attributes>
              </ProvisioningPlan>
            </value>
          </entry>
        </Map>
      </Attributes>
    </IdentityRequestItem>
    <IdentityRequestItem application="Sales Analytics" approvalState="Finished" compilationStatus="Expansion" expansionCause="ProvisioningPolicy" name="region" nativeIdentity="8512519" operation="Set" provisioningEngine="Sales Analytics" provisioningState="Failed" value="A">
      <Attributes>
        <Map>
          <entry key="attachmentConfigList"/>
          <entry key="attachments"/>
          <entry key="errors">
            <value>
              <List>
                <Message key="java.sql.SQLIntegrityConstraintViolationException: Duplicate entry '8512519' for key 'salesemployee.PRIMARY'" type="Error"/>
              </List>
            </value>
          </entry>
          <entry key="expansionInfo" value="Sales Analytics"/>
          <entry key="flow" value="AccessRequest"/>
          <entry key="id" value="c0a83c019a0c102b819a1038f4ca0502"/>
          <entry key="interface" value="LCM"/>
          <entry key="managedAttributeType" value="Entitlement"/>
          <entry key="nativeIdUpdated">
            <value>
              <Boolean>true</Boolean>
            </value>
          </entry>
          <entry key="operation" value="EntitlementAdd"/>
          <entry key="provisioningPlan">
            <value>
              <ProvisioningPlan trackingId="b1321e59a52249d3b4ff7369e2888844">
                <AccountRequest application="Sales Analytics" nativeIdentity="8512519" op="Create">
                  <Attributes>
                    <Map>
                      <entry key="attachmentConfigList"/>
                      <entry key="attachments"/>
                      <entry key="flow" value="AccessRequest"/>
                      <entry key="id" value="c0a83c019a0c102b819a1038f4ca0502"/>
                      <entry key="interface" value="LCM"/>
                      <entry key="nativeIdUpdated">
                        <value>
                          <Boolean>true</Boolean>
                        </value>
                      </entry>
                      <entry key="operation" value="EntitlementAdd"/>
                      <entry key="provisioningTransactionId" value="c0a83c019b731761819bb22fa55a2511"/>
                    </Map>
                  </Attributes>
                  <AttributeRequest name="region" op="Set" trackingId="b1321e59a52249d3b4ff7369e2888844" value="A"/>
                </AccountRequest>
                <Attributes>
                  <Map>
                    <entry key="source" value="LCM"/>
                  </Map>
                </Attributes>
              </ProvisioningPlan>
            </value>
          </entry>
        </Map>
      </Attributes>
    </IdentityRequestItem>
    <IdentityRequestItem application="Sales Analytics" approvalState="Finished" compilationStatus="Expansion" expansionCause="ProvisioningPolicy" name="territory" nativeIdentity="8512519" operation="Set" provisioningEngine="Sales Analytics" provisioningState="Failed" value="A">
      <Attributes>
        <Map>
          <entry key="attachmentConfigList"/>
          <entry key="attachments"/>
          <entry key="errors">
            <value>
              <List>
                <Message key="java.sql.SQLIntegrityConstraintViolationException: Duplicate entry '8512519' for key 'salesemployee.PRIMARY'" type="Error"/>
              </List>
            </value>
          </entry>
          <entry key="expansionInfo" value="Sales Analytics"/>
          <entry key="flow" value="AccessRequest"/>
          <entry key="id" value="c0a83c019a0c102b819a1038f4ca0502"/>
          <entry key="interface" value="LCM"/>
          <entry key="managedAttributeType" value="Entitlement"/>
          <entry key="nativeIdUpdated">
            <value>
              <Boolean>true</Boolean>
            </value>
          </entry>
          <entry key="operation" value="EntitlementAdd"/>
          <entry key="provisioningPlan">
            <value>
              <ProvisioningPlan trackingId="3d8769b428a14b7796ba2cacb9d4d9f8">
                <AccountRequest application="Sales Analytics" nativeIdentity="8512519" op="Create">
                  <Attributes>
                    <Map>
                      <entry key="attachmentConfigList"/>
                      <entry key="attachments"/>
                      <entry key="flow" value="AccessRequest"/>
                      <entry key="id" value="c0a83c019a0c102b819a1038f4ca0502"/>
                      <entry key="interface" value="LCM"/>
                      <entry key="nativeIdUpdated">
                        <value>
                          <Boolean>true</Boolean>
                        </value>
                      </entry>
                      <entry key="operation" value="EntitlementAdd"/>
                      <entry key="provisioningTransactionId" value="c0a83c019b731761819bb22fa55a2511"/>
                    </Map>
                  </Attributes>
                  <AttributeRequest name="territory" op="Set" trackingId="3d8769b428a14b7796ba2cacb9d4d9f8" value="A"/>
                </AccountRequest>
                <Attributes>
                  <Map>
                    <entry key="source" value="LCM"/>
                  </Map>
                </Attributes>
              </ProvisioningPlan>
            </value>
          </entry>
        </Map>
      </Attributes>
    </IdentityRequestItem>
    <IdentityRequestItem application="Sales Analytics" approvalState="Finished" compilationStatus="Expansion" expansionCause="ProvisioningPolicy" name="commissionRate" nativeIdentity="8512519" operation="Set" provisioningEngine="Sales Analytics" provisioningState="Failed" value="5%">
      <Attributes>
        <Map>
          <entry key="attachmentConfigList"/>
          <entry key="attachments"/>
          <entry key="errors">
            <value>
              <List>
                <Message key="java.sql.SQLIntegrityConstraintViolationException: Duplicate entry '8512519' for key 'salesemployee.PRIMARY'" type="Error"/>
              </List>
            </value>
          </entry>
          <entry key="expansionInfo" value="Sales Analytics"/>
          <entry key="flow" value="AccessRequest"/>
          <entry key="id" value="c0a83c019a0c102b819a1038f4ca0502"/>
          <entry key="interface" value="LCM"/>
          <entry key="managedAttributeType" value="Entitlement"/>
          <entry key="nativeIdUpdated">
            <value>
              <Boolean>true</Boolean>
            </value>
          </entry>
          <entry key="operation" value="EntitlementAdd"/>
          <entry key="provisioningPlan">
            <value>
              <ProvisioningPlan trackingId="f9669dfae7944290ae2cea2da1e667c5">
                <AccountRequest application="Sales Analytics" nativeIdentity="8512519" op="Create">
                  <Attributes>
                    <Map>
                      <entry key="attachmentConfigList"/>
                      <entry key="attachments"/>
                      <entry key="flow" value="AccessRequest"/>
                      <entry key="id" value="c0a83c019a0c102b819a1038f4ca0502"/>
                      <entry key="interface" value="LCM"/>
                      <entry key="nativeIdUpdated">
                        <value>
                          <Boolean>true</Boolean>
                        </value>
                      </entry>
                      <entry key="operation" value="EntitlementAdd"/>
                      <entry key="provisioningTransactionId" value="c0a83c019b731761819bb22fa55a2511"/>
                    </Map>
                  </Attributes>
                  <AttributeRequest name="commissionRate" op="Set" trackingId="f9669dfae7944290ae2cea2da1e667c5" value="5%"/>
                </AccountRequest>
                <Attributes>
                  <Map>
                    <entry key="source" value="LCM"/>
                  </Map>
                </Attributes>
              </ProvisioningPlan>
            </value>
          </entry>
        </Map>
      </Attributes>
    </IdentityRequestItem>
    <IdentityRequestItem application="Sales Analytics" approvalState="Finished" compilationStatus="Expansion" expansionCause="ProvisioningPolicy" name="managerId" nativeIdentity="8512519" operation="Set" provisioningEngine="Sales Analytics" provisioningState="Failed" value="c06fe45e-ee86-4c73-8bdb-73ca28e2cd69">
      <Attributes>
        <Map>
          <entry key="attachmentConfigList"/>
          <entry key="attachments"/>
          <entry key="errors">
            <value>
              <List>
                <Message key="java.sql.SQLIntegrityConstraintViolationException: Duplicate entry '8512519' for key 'salesemployee.PRIMARY'" type="Error"/>
              </List>
            </value>
          </entry>
          <entry key="expansionInfo" value="Sales Analytics"/>
          <entry key="flow" value="AccessRequest"/>
          <entry key="id" value="c0a83c019a0c102b819a1038f4ca0502"/>
          <entry key="interface" value="LCM"/>
          <entry key="managedAttributeType" value="Entitlement"/>
          <entry key="nativeIdUpdated">
            <value>
              <Boolean>true</Boolean>
            </value>
          </entry>
          <entry key="operation" value="EntitlementAdd"/>
          <entry key="provisioningPlan">
            <value>
              <ProvisioningPlan trackingId="761b66be0ccd4be58324fded46890f0d">
                <AccountRequest application="Sales Analytics" nativeIdentity="8512519" op="Create">
                  <Attributes>
                    <Map>
                      <entry key="attachmentConfigList"/>
                      <entry key="attachments"/>
                      <entry key="flow" value="AccessRequest"/>
                      <entry key="id" value="c0a83c019a0c102b819a1038f4ca0502"/>
                      <entry key="interface" value="LCM"/>
                      <entry key="nativeIdUpdated">
                        <value>
                          <Boolean>true</Boolean>
                        </value>
                      </entry>
                      <entry key="operation" value="EntitlementAdd"/>
                      <entry key="provisioningTransactionId" value="c0a83c019b731761819bb22fa55a2511"/>
                    </Map>
                  </Attributes>
                  <AttributeRequest name="managerId" op="Set" trackingId="761b66be0ccd4be58324fded46890f0d" value="c06fe45e-ee86-4c73-8bdb-73ca28e2cd69"/>
                </AccountRequest>
                <Attributes>
                  <Map>
                    <entry key="source" value="LCM"/>
                  </Map>
                </Attributes>
              </ProvisioningPlan>
            </value>
          </entry>
        </Map>
      </Attributes>
    </IdentityRequestItem>
    <IdentityRequestItem application="Sales Analytics" approvalState="Finished" compilationStatus="Expansion" expansionCause="ProvisioningPolicy" name="annualHours" nativeIdentity="8512519" operation="Set" provisioningEngine="Sales Analytics" provisioningState="Failed" value="720">
      <Attributes>
        <Map>
          <entry key="attachmentConfigList"/>
          <entry key="attachments"/>
          <entry key="errors">
            <value>
              <List>
                <Message key="java.sql.SQLIntegrityConstraintViolationException: Duplicate entry '8512519' for key 'salesemployee.PRIMARY'" type="Error"/>
              </List>
            </value>
          </entry>
          <entry key="expansionInfo" value="Sales Analytics"/>
          <entry key="flow" value="AccessRequest"/>
          <entry key="id" value="c0a83c019a0c102b819a1038f4ca0502"/>
          <entry key="interface" value="LCM"/>
          <entry key="managedAttributeType" value="Entitlement"/>
          <entry key="nativeIdUpdated">
            <value>
              <Boolean>true</Boolean>
            </value>
          </entry>
          <entry key="operation" value="EntitlementAdd"/>
          <entry key="provisioningPlan">
            <value>
              <ProvisioningPlan trackingId="3868a4190c614e5ba25202f484e7f65f">
                <AccountRequest application="Sales Analytics" nativeIdentity="8512519" op="Create">
                  <Attributes>
                    <Map>
                      <entry key="attachmentConfigList"/>
                      <entry key="attachments"/>
                      <entry key="flow" value="AccessRequest"/>
                      <entry key="id" value="c0a83c019a0c102b819a1038f4ca0502"/>
                      <entry key="interface" value="LCM"/>
                      <entry key="nativeIdUpdated">
                        <value>
                          <Boolean>true</Boolean>
                        </value>
                      </entry>
                      <entry key="operation" value="EntitlementAdd"/>
                      <entry key="provisioningTransactionId" value="c0a83c019b731761819bb22fa55a2511"/>
                    </Map>
                  </Attributes>
                  <AttributeRequest name="annualHours" op="Set" trackingId="3868a4190c614e5ba25202f484e7f65f" value="720"/>
                </AccountRequest>
                <Attributes>
                  <Map>
                    <entry key="source" value="LCM"/>
                  </Map>
                </Attributes>
              </ProvisioningPlan>
            </value>
          </entry>
        </Map>
      </Attributes>
    </IdentityRequestItem>
    <IdentityRequestItem application="Sales Analytics" approvalState="Finished" compilationStatus="Expansion" expansionCause="ProvisioningPolicy" name="jobTitle" nativeIdentity="8512519" operation="Set" provisioningEngine="Sales Analytics" provisioningState="Failed" value="Product Manager-test">
      <Attributes>
        <Map>
          <entry key="attachmentConfigList"/>
          <entry key="attachments"/>
          <entry key="errors">
            <value>
              <List>
                <Message key="java.sql.SQLIntegrityConstraintViolationException: Duplicate entry '8512519' for key 'salesemployee.PRIMARY'" type="Error"/>
              </List>
            </value>
          </entry>
          <entry key="expansionInfo" value="Sales Analytics"/>
          <entry key="flow" value="AccessRequest"/>
          <entry key="id" value="c0a83c019a0c102b819a1038f4ca0502"/>
          <entry key="interface" value="LCM"/>
          <entry key="managedAttributeType" value="Entitlement"/>
          <entry key="nativeIdUpdated">
            <value>
              <Boolean>true</Boolean>
            </value>
          </entry>
          <entry key="operation" value="EntitlementAdd"/>
          <entry key="provisioningPlan">
            <value>
              <ProvisioningPlan trackingId="d29c6a42b640418ca014d122a7a96ee3">
                <AccountRequest application="Sales Analytics" nativeIdentity="8512519" op="Create">
                  <Attributes>
                    <Map>
                      <entry key="attachmentConfigList"/>
                      <entry key="attachments"/>
                      <entry key="flow" value="AccessRequest"/>
                      <entry key="id" value="c0a83c019a0c102b819a1038f4ca0502"/>
                      <entry key="interface" value="LCM"/>
                      <entry key="nativeIdUpdated">
                        <value>
                          <Boolean>true</Boolean>
                        </value>
                      </entry>
                      <entry key="operation" value="EntitlementAdd"/>
                      <entry key="provisioningTransactionId" value="c0a83c019b731761819bb22fa55a2511"/>
                    </Map>
                  </Attributes>
                  <AttributeRequest name="jobTitle" op="Set" trackingId="d29c6a42b640418ca014d122a7a96ee3" value="Product Manager-test"/>
                </AccountRequest>
                <Attributes>
                  <Map>
                    <entry key="source" value="LCM"/>
                  </Map>
                </Attributes>
              </ProvisioningPlan>
            </value>
          </entry>
        </Map>
      </Attributes>
    </IdentityRequestItem>
    <IdentityRequestItem application="Sales Analytics" approvalState="Finished" compilationStatus="Expansion" expansionCause="ProvisioningPolicy" name="country" nativeIdentity="8512519" operation="Set" provisioningEngine="Sales Analytics" provisioningState="Failed" value="China">
      <Attributes>
        <Map>
          <entry key="attachmentConfigList"/>
          <entry key="attachments"/>
          <entry key="errors">
            <value>
              <List>
                <Message key="java.sql.SQLIntegrityConstraintViolationException: Duplicate entry '8512519' for key 'salesemployee.PRIMARY'" type="Error"/>
              </List>
            </value>
          </entry>
          <entry key="expansionInfo" value="Sales Analytics"/>
          <entry key="flow" value="AccessRequest"/>
          <entry key="id" value="c0a83c019a0c102b819a1038f4ca0502"/>
          <entry key="interface" value="LCM"/>
          <entry key="managedAttributeType" value="Entitlement"/>
          <entry key="nativeIdUpdated">
            <value>
              <Boolean>true</Boolean>
            </value>
          </entry>
          <entry key="operation" value="EntitlementAdd"/>
          <entry key="provisioningPlan">
            <value>
              <ProvisioningPlan trackingId="b684fec85328407a85a2a16d5ad2c509">
                <AccountRequest application="Sales Analytics" nativeIdentity="8512519" op="Create">
                  <Attributes>
                    <Map>
                      <entry key="attachmentConfigList"/>
                      <entry key="attachments"/>
                      <entry key="flow" value="AccessRequest"/>
                      <entry key="id" value="c0a83c019a0c102b819a1038f4ca0502"/>
                      <entry key="interface" value="LCM"/>
                      <entry key="nativeIdUpdated">
                        <value>
                          <Boolean>true</Boolean>
                        </value>
                      </entry>
                      <entry key="operation" value="EntitlementAdd"/>
                      <entry key="provisioningTransactionId" value="c0a83c019b731761819bb22fa55a2511"/>
                    </Map>
                  </Attributes>
                  <AttributeRequest name="country" op="Set" trackingId="b684fec85328407a85a2a16d5ad2c509" value="China"/>
                </AccountRequest>
                <Attributes>
                  <Map>
                    <entry key="source" value="LCM"/>
                  </Map>
                </Attributes>
              </ProvisioningPlan>
            </value>
          </entry>
        </Map>
      </Attributes>
    </IdentityRequestItem>
    <IdentityRequestItem application="Sales Analytics" approvalState="Finished" compilationStatus="Expansion" expansionCause="ProvisioningPolicy" name="isManager" nativeIdentity="8512519" operation="Set" provisioningEngine="Sales Analytics" provisioningState="Failed" value="No">
      <Attributes>
        <Map>
          <entry key="attachmentConfigList"/>
          <entry key="attachments"/>
          <entry key="errors">
            <value>
              <List>
                <Message key="java.sql.SQLIntegrityConstraintViolationException: Duplicate entry '8512519' for key 'salesemployee.PRIMARY'" type="Error"/>
              </List>
            </value>
          </entry>
          <entry key="expansionInfo" value="Sales Analytics"/>
          <entry key="flow" value="AccessRequest"/>
          <entry key="id" value="c0a83c019a0c102b819a1038f4ca0502"/>
          <entry key="interface" value="LCM"/>
          <entry key="managedAttributeType" value="Entitlement"/>
          <entry key="nativeIdUpdated">
            <value>
              <Boolean>true</Boolean>
            </value>
          </entry>
          <entry key="operation" value="EntitlementAdd"/>
          <entry key="provisioningPlan">
            <value>
              <ProvisioningPlan trackingId="6d910bc28d414725b7227b21b8463bee">
                <AccountRequest application="Sales Analytics" nativeIdentity="8512519" op="Create">
                  <Attributes>
                    <Map>
                      <entry key="attachmentConfigList"/>
                      <entry key="attachments"/>
                      <entry key="flow" value="AccessRequest"/>
                      <entry key="id" value="c0a83c019a0c102b819a1038f4ca0502"/>
                      <entry key="interface" value="LCM"/>
                      <entry key="nativeIdUpdated">
                        <value>
                          <Boolean>true</Boolean>
                        </value>
                      </entry>
                      <entry key="operation" value="EntitlementAdd"/>
                      <entry key="provisioningTransactionId" value="c0a83c019b731761819bb22fa55a2511"/>
                    </Map>
                  </Attributes>
                  <AttributeRequest name="isManager" op="Set" trackingId="6d910bc28d414725b7227b21b8463bee" value="No"/>
                </AccountRequest>
                <Attributes>
                  <Map>
                    <entry key="source" value="LCM"/>
                  </Map>
                </Attributes>
              </ProvisioningPlan>
            </value>
          </entry>
        </Map>
      </Attributes>
    </IdentityRequestItem>
    <IdentityRequestItem application="Sales Analytics" approvalState="Finished" compilationStatus="Expansion" expansionCause="ProvisioningPolicy" name="businessUnit" nativeIdentity="8512519" operation="Set" provisioningEngine="Sales Analytics" provisioningState="Failed" value="A">
      <Attributes>
        <Map>
          <entry key="attachmentConfigList"/>
          <entry key="attachments"/>
          <entry key="errors">
            <value>
              <List>
                <Message key="java.sql.SQLIntegrityConstraintViolationException: Duplicate entry '8512519' for key 'salesemployee.PRIMARY'" type="Error"/>
              </List>
            </value>
          </entry>
          <entry key="expansionInfo" value="Sales Analytics"/>
          <entry key="flow" value="AccessRequest"/>
          <entry key="id" value="c0a83c019a0c102b819a1038f4ca0502"/>
          <entry key="interface" value="LCM"/>
          <entry key="managedAttributeType" value="Entitlement"/>
          <entry key="nativeIdUpdated">
            <value>
              <Boolean>true</Boolean>
            </value>
          </entry>
          <entry key="operation" value="EntitlementAdd"/>
          <entry key="provisioningPlan">
            <value>
              <ProvisioningPlan trackingId="ad924c2179834d44911eac6871576c5c">
                <AccountRequest application="Sales Analytics" nativeIdentity="8512519" op="Create">
                  <Attributes>
                    <Map>
                      <entry key="attachmentConfigList"/>
                      <entry key="attachments"/>
                      <entry key="flow" value="AccessRequest"/>
                      <entry key="id" value="c0a83c019a0c102b819a1038f4ca0502"/>
                      <entry key="interface" value="LCM"/>
                      <entry key="nativeIdUpdated">
                        <value>
                          <Boolean>true</Boolean>
                        </value>
                      </entry>
                      <entry key="operation" value="EntitlementAdd"/>
                      <entry key="provisioningTransactionId" value="c0a83c019b731761819bb22fa55a2511"/>
                    </Map>
                  </Attributes>
                  <AttributeRequest name="businessUnit" op="Set" trackingId="ad924c2179834d44911eac6871576c5c" value="A"/>
                </AccountRequest>
                <Attributes>
                  <Map>
                    <entry key="source" value="LCM"/>
                  </Map>
                </Attributes>
              </ProvisioningPlan>
            </value>
          </entry>
        </Map>
      </Attributes>
    </IdentityRequestItem>
    <IdentityRequestItem application="Sales Analytics" compilationStatus="Expansion" nativeIdentity="8512519" operation="Create" provisioningEngine="Sales Analytics" provisioningState="Failed">
      <Attributes>
        <Map>
          <entry key="attachmentConfigList"/>
          <entry key="attachments"/>
          <entry key="errors">
            <value>
              <List>
                <Message key="java.sql.SQLIntegrityConstraintViolationException: Duplicate entry '8512519' for key 'salesemployee.PRIMARY'" type="Error"/>
              </List>
            </value>
          </entry>
          <entry key="flow" value="AccessRequest"/>
          <entry key="id" value="c0a83c019a0c102b819a1038f4ca0502"/>
          <entry key="interface" value="LCM"/>
          <entry key="nativeIdUpdated">
            <value>
              <Boolean>true</Boolean>
            </value>
          </entry>
          <entry key="operation" value="EntitlementAdd"/>
          <entry key="provisioningPlan">
            <value>
              <ProvisioningPlan trackingId="43a6c76291e54c2b8ffbb99af7e7dec3">
                <AccountRequest application="Sales Analytics" nativeIdentity="8512519" op="Create">
                  <Attributes>
                    <Map>
                      <entry key="attachmentConfigList"/>
                      <entry key="attachments"/>
                      <entry key="flow" value="AccessRequest"/>
                      <entry key="id" value="c0a83c019a0c102b819a1038f4ca0502"/>
                      <entry key="interface" value="LCM"/>
                      <entry key="nativeIdUpdated">
                        <value>
                          <Boolean>true</Boolean>
                        </value>
                      </entry>
                      <entry key="operation" value="EntitlementAdd"/>
                      <entry key="provisioningTransactionId" value="c0a83c019b731761819bb22fa55a2511"/>
                    </Map>
                  </Attributes>
                </AccountRequest>
                <Attributes>
                  <Map>
                    <entry key="source" value="LCM"/>
                  </Map>
                </Attributes>
              </ProvisioningPlan>
            </value>
          </entry>
        </Map>
      </Attributes>
    </IdentityRequestItem>
  </RequestItems>
</IdentityRequest>