<?xml version='1.0' encoding='UTF-8'?>
<!DOCTYPE IdentityRequest PUBLIC "sailpoint.dtd" "sailpoint.dtd">
<IdentityRequest completionStatus="Success" endDate="1768832375968" executionStatus="Completed" name="0000000330" priority="Normal" requesterDisplayName="Scheduler" source="LCM" state="End" targetClass="sailpoint.object.Identity" targetDisplayName="William Garcia" verified="1768832375968">
  <Attributes>
    <Map>
      <entry key="provisionedProject">
        <value>
          <ProvisioningProject identity="9bcaa225-f0c4-405a-8895-2159b92fb553">
            <Attributes>
              <Map>
                <entry key="disableRetryRequest">
                  <value>
                    <Boolean>true</Boolean>
                  </value>
                </entry>
                <entry key="identityRequestId" value="0000000330"/>
                <entry key="optimisticProvisioning" value="false"/>
                <entry key="requester" value="Scheduler"/>
                <entry key="source" value="LCM"/>
              </Map>
            </Attributes>
            <MasterPlan>
              <ProvisioningPlan>
                <Attributes>
                  <Map>
                    <entry key="identityRequestId" value="0000000330"/>
                    <entry key="requester" value="Scheduler"/>
                    <entry key="source" value="LCM"/>
                  </Map>
                </Attributes>
              </ProvisioningPlan>
            </MasterPlan>
          </ProvisioningProject>
        </value>
      </entry>
      <entry key="taskResultId" value="c0a83c019bd11f47819bd69fd4560312"/>
    </Map>
  </Attributes>
</IdentityRequest>