<?xml version='1.0' encoding='UTF-8'?>
<!DOCTYPE IdentityRequest PUBLIC "sailpoint.dtd" "sailpoint.dtd">
<IdentityRequest completionStatus="Success" endDate="1768478219399" executionStatus="Completed" name="0000000320" priority="Normal" requesterDisplayName="The Administrator" requesterId="c0a83c0199cf13658199cf93c73500fe" source="LCM" state="End" targetClass="Identity" targetDisplayName="Hector Petty" type="AccountsRequest" verified="1768542752674">
  <Attributes>
    <Map>
      <entry key="provisionedProject">
        <value>
          <ProvisioningProject identity="3ae9ccae-0c70-4dda-a43e-2654222f32a8">
            <Attributes>
              <Map>
                <entry key="disableRetryRequest">
                  <value>
                    <Boolean>true</Boolean>
                  </value>
                </entry>
                <entry key="identityRequestId" value="0000000320"/>
                <entry key="optimisticProvisioning" value="false"/>
                <entry key="requester" value="spadmin"/>
                <entry key="source" value="LCM"/>
              </Map>
            </Attributes>
            <MasterPlan>
              <ProvisioningPlan>
                <AccountRequest application="Financial Planning &amp; Forecasting" nativeIdentity="739092" op="Enable">
                  <Attributes>
                    <Map>
                      <entry key="flow" value="AccountsRequest"/>
                      <entry key="interface" value="LCM"/>
                      <entry key="operation" value="Enable"/>
                    </Map>
                  </Attributes>
                </AccountRequest>
                <AccountRequest application="Sales Analytics" nativeIdentity="739092" op="Disable">
                  <Attributes>
                    <Map>
                      <entry key="flow" value="AccountsRequest"/>
                      <entry key="interface" value="LCM"/>
                      <entry key="operation" value="Disable"/>
                    </Map>
                  </Attributes>
                </AccountRequest>
                <Attributes>
                  <Map>
                    <entry key="identityRequestId" value="0000000320"/>
                    <entry key="requester" value="spadmin"/>
                    <entry key="source" value="LCM"/>
                  </Map>
                </Attributes>
              </ProvisioningPlan>
            </MasterPlan>
            <ProvisioningPlan nativeIdentity="3ae9ccae-0c70-4dda-a43e-2654222f32a8" targetIntegration="Sales Analytics" trackingId="0b60cfd1409545e1a5dc85907876b489">
              <AccountRequest application="Sales Analytics" nativeIdentity="739092" op="Disable" targetIntegration="Sales Analytics">
                <Attributes>
                  <Map>
                    <entry key="flow" value="AccountsRequest"/>
                    <entry key="interface" value="LCM"/>
                    <entry key="operation" value="Disable"/>
                  </Map>
                </Attributes>
                <AttributeRequest name="status" op="Set" value="Inactive"/>
                <AttributeRequest name="terminationDate" op="Set" value="01-15-2026"/>
                <ProvisioningResult status="committed"/>
              </AccountRequest>
              <Attributes>
                <Map>
                  <entry key="identityRequestId" value="0000000320"/>
                  <entry key="requester" value="spadmin"/>
                  <entry key="source" value="LCM"/>
                </Map>
              </Attributes>
              <ProvisioningResult status="committed"/>
            </ProvisioningPlan>
            <ProvisioningPlan nativeIdentity="3ae9ccae-0c70-4dda-a43e-2654222f32a8" targetIntegration="Financial Planning &amp; Forecasting" trackingId="74a09cc984dc412b8d4b939db9fb87bc">
              <AccountRequest application="Financial Planning &amp; Forecasting" nativeIdentity="739092" op="Enable" targetIntegration="Financial Planning &amp; Forecasting">
                <Attributes>
                  <Map>
                    <entry key="flow" value="AccountsRequest"/>
                    <entry key="interface" value="LCM"/>
                    <entry key="operation" value="Enable"/>
                  </Map>
                </Attributes>
                <AttributeRequest name="empStatus" op="Set" value="Active"/>
                <ProvisioningResult status="committed"/>
              </AccountRequest>
              <Attributes>
                <Map>
                  <entry key="identityRequestId" value="0000000320"/>
                  <entry key="requester" value="spadmin"/>
                  <entry key="source" value="LCM"/>
                </Map>
              </Attributes>
              <ProvisioningResult status="committed"/>
            </ProvisioningPlan>
            <ProvisioningTarget retain="true" role="SR_Role_Active_Directory_Basic_Access">
              <AccountSelection applicationId="c0a83c0199d417218199d43c5f300017" applicationName="Active Directory" doCreate="true"/>
            </ProvisioningTarget>
          </ProvisioningProject>
        </value>
      </entry>
      <entry key="taskResultId" value="c0a83c019bc11445819bc18413880038"/>
    </Map>
  </Attributes>
  <RequestItems>
    <IdentityRequestItem application="Financial Planning &amp; Forecasting" approvalState="Finished" nativeIdentity="739092" operation="Enable" ownerName="spadmin" provisioningState="Finished">
      <Attributes>
        <Map>
          <entry key="flow" value="AccountsRequest"/>
          <entry key="interface" value="LCM"/>
          <entry key="operation" value="Enable"/>
          <entry key="provisioningPlan">
            <value>
              <ProvisioningPlan trackingId="634ee916657c4f81b595a3fb5326dd99">
                <AccountRequest application="Financial Planning &amp; Forecasting" nativeIdentity="739092" op="Enable">
                  <Attributes>
                    <Map>
                      <entry key="flow" value="AccountsRequest"/>
                      <entry key="interface" value="LCM"/>
                      <entry key="operation" value="Enable"/>
                    </Map>
                  </Attributes>
                </AccountRequest>
                <Attributes>
                  <Map>
                    <entry key="source" value="LCM"/>
                  </Map>
                </Attributes>
              </ProvisioningPlan>
            </value>
          </entry>
        </Map>
      </Attributes>
      <Owner>
        <Reference class="sailpoint.object.Identity" name="spadmin"/>
      </Owner>
    </IdentityRequestItem>
    <IdentityRequestItem application="Sales Analytics" approvalState="Finished" nativeIdentity="739092" operation="Disable" ownerName="spadmin" provisioningState="Finished">
      <Attributes>
        <Map>
          <entry key="flow" value="AccountsRequest"/>
          <entry key="interface" value="LCM"/>
          <entry key="operation" value="Disable"/>
          <entry key="provisioningPlan">
            <value>
              <ProvisioningPlan trackingId="58e7088731b849c2a9751876c8e89adb">
                <AccountRequest application="Sales Analytics" nativeIdentity="739092" op="Disable">
                  <Attributes>
                    <Map>
                      <entry key="flow" value="AccountsRequest"/>
                      <entry key="interface" value="LCM"/>
                      <entry key="operation" value="Disable"/>
                    </Map>
                  </Attributes>
                </AccountRequest>
                <Attributes>
                  <Map>
                    <entry key="source" value="LCM"/>
                  </Map>
                </Attributes>
              </ProvisioningPlan>
            </value>
          </entry>
        </Map>
      </Attributes>
      <Owner>
        <Reference class="sailpoint.object.Identity" name="spadmin"/>
      </Owner>
    </IdentityRequestItem>
    <IdentityRequestItem application="Sales Analytics" approvalState="Finished" compilationStatus="Expansion" expansionCause="ProvisioningPolicy" name="status" nativeIdentity="739092" operation="Set" provisioningEngine="Sales Analytics" provisioningState="Finished" value="Inactive">
      <Attributes>
        <Map>
          <entry key="expansionInfo" value="Sales Analytics"/>
          <entry key="flow" value="AccountsRequest"/>
          <entry key="interface" value="LCM"/>
          <entry key="managedAttributeType" value="Entitlement"/>
          <entry key="operation" value="Disable"/>
          <entry key="provisioningPlan">
            <value>
              <ProvisioningPlan trackingId="0936915cb982438f9ba1541e147eb2d2">
                <AccountRequest application="Sales Analytics" nativeIdentity="739092" op="Disable" targetIntegration="Sales Analytics">
                  <Attributes>
                    <Map>
                      <entry key="flow" value="AccountsRequest"/>
                      <entry key="interface" value="LCM"/>
                      <entry key="operation" value="Disable"/>
                    </Map>
                  </Attributes>
                  <AttributeRequest name="status" op="Set" trackingId="0936915cb982438f9ba1541e147eb2d2" value="Inactive"/>
                </AccountRequest>
                <Attributes>
                  <Map>
                    <entry key="source" value="LCM"/>
                  </Map>
                </Attributes>
              </ProvisioningPlan>
            </value>
          </entry>
        </Map>
      </Attributes>
    </IdentityRequestItem>
    <IdentityRequestItem application="Sales Analytics" approvalState="Finished" compilationStatus="Expansion" expansionCause="ProvisioningPolicy" name="terminationDate" nativeIdentity="739092" operation="Set" provisioningEngine="Sales Analytics" provisioningState="Finished" value="01-15-2026">
      <Attributes>
        <Map>
          <entry key="expansionInfo" value="Sales Analytics"/>
          <entry key="flow" value="AccountsRequest"/>
          <entry key="interface" value="LCM"/>
          <entry key="managedAttributeType" value="Entitlement"/>
          <entry key="operation" value="Disable"/>
          <entry key="provisioningPlan">
            <value>
              <ProvisioningPlan trackingId="e14d3cfde2834e63a402223ef2601472">
                <AccountRequest application="Sales Analytics" nativeIdentity="739092" op="Disable" targetIntegration="Sales Analytics">
                  <Attributes>
                    <Map>
                      <entry key="flow" value="AccountsRequest"/>
                      <entry key="interface" value="LCM"/>
                      <entry key="operation" value="Disable"/>
                    </Map>
                  </Attributes>
                  <AttributeRequest name="terminationDate" op="Set" trackingId="e14d3cfde2834e63a402223ef2601472" value="01-15-2026"/>
                </AccountRequest>
                <Attributes>
                  <Map>
                    <entry key="source" value="LCM"/>
                  </Map>
                </Attributes>
              </ProvisioningPlan>
            </value>
          </entry>
        </Map>
      </Attributes>
    </IdentityRequestItem>
    <IdentityRequestItem application="Financial Planning &amp; Forecasting" approvalState="Finished" compilationStatus="Expansion" expansionCause="ProvisioningPolicy" name="empStatus" nativeIdentity="739092" operation="Set" provisioningEngine="Financial Planning &amp; Forecasting" provisioningState="Finished" value="Active">
      <Attributes>
        <Map>
          <entry key="expansionInfo" value="Financial Planning &amp; Forecasting"/>
          <entry key="flow" value="AccountsRequest"/>
          <entry key="interface" value="LCM"/>
          <entry key="managedAttributeType" value="Entitlement"/>
          <entry key="operation" value="Enable"/>
          <entry key="provisioningPlan">
            <value>
              <ProvisioningPlan trackingId="94e451635a9c40b2bfab71ef5ddf95ba">
                <AccountRequest application="Financial Planning &amp; Forecasting" nativeIdentity="739092" op="Enable" targetIntegration="Financial Planning &amp; Forecasting">
                  <Attributes>
                    <Map>
                      <entry key="flow" value="AccountsRequest"/>
                      <entry key="interface" value="LCM"/>
                      <entry key="operation" value="Enable"/>
                    </Map>
                  </Attributes>
                  <AttributeRequest name="empStatus" op="Set" trackingId="94e451635a9c40b2bfab71ef5ddf95ba" value="Active"/>
                </AccountRequest>
                <Attributes>
                  <Map>
                    <entry key="source" value="LCM"/>
                  </Map>
                </Attributes>
              </ProvisioningPlan>
            </value>
          </entry>
        </Map>
      </Attributes>
    </IdentityRequestItem>
  </RequestItems>
</IdentityRequest>